stuscraper/__init__.py
stuscraper/bootstrap.py
stuscraper/dbmanipulation.py
stuscraper/search.py
stuscraper/stu_download.py
stuscraper/stu_imgdl.py
stuscraper/usercounter.py
stuscraper-1.0.0.dist-info/LICENCE
stuscraper-1.0.0.dist-info/METADATA
stuscraper-1.0.0.dist-info/WHEEL
stuscraper-1.0.0.dist-info/entry_points.txt
stuscraper-1.0.0.dist-info/top_level.txt
stuscraper-1.0.0.dist-info/RECORD
