Metadata-Version: 2.1
Name: stuscraper
Version: 1.0.0
Summary: Stuscraper is a CLI for *.ope.ee based Stuudium sites
Home-page: https://github.com/goldenbeasty/stuscraper
Author: Goldenbeasty
Author-email: goldenbeaster@gmail.com
License: GNU General Public License v3 (GPLv3)
Project-URL: Docs, https://github.com/goldenbeasty/stuscraper
Classifier: Programming Language :: Python :: 3
Classifier: License :: OSI Approved :: GNU General Public License v3 (GPLv3)
Classifier: Operating System :: OS Independent
Requires-Python: >=3.6
License-File: src/stuscraper/LICENCE
Requires-Dist: requests
Requires-Dist: Pillow
Requires-Dist: bs4
Requires-Dist: lxml
